Workbook

Sheet Zone Density Dashboard
A1: AI INSIGHT SUMMARY: Your North zone yields $142/drive-hour with 12 stops packed into 6 miles -- this is your profit engine; accept any new customer here, even at a 15% discount. Your Far-West zone yields only $38/drive-hour across 3 scattered stops over 19 miles, which is below your $65/hour breakeven -- decline new west-side prospects unless they accept a $40 distance premium. The West territory as a whole has crossed into abandon economics; selling or trading those 3 stops to a competitor would free 4.2 drive-hours per week. Apply the New Customer Calculator before booking any prospect: it scored the sample prospect in Zone 4 as DECLINE because their zone yields under breakeven and adding them lengthens an already thin route.
A5: Zone Name | B5: Stops | C5: Service Radius (mi) | D5: Monthly Revenue | E5: Drive Hours / Month | F5: Breakeven $/Drive-Hour | G5: Revenue per Drive-Hour | H5: Stops per Mile | I5: Avg Revenue per Stop | J5: Zone Verdict
A6: North | B6: 12 | C6: 6 | D6: 1700 | E6: 12 | F6: 65 | G6: =IFERROR(IF(E6=0,0,D6/E6),"") | H6: =IFERROR(IF(C6=0,0,B6/C6),"") | I6: =IFERROR(IF(B6=0,0,D6/B6),"") | J6: =IFERROR(IF(G6<F6,"ABANDON - below breakeven, sell/trade route",IF(G6<F6*1.5,"SURCHARGE - accept only with distance premium","ACCEPT - prime zone, take new customers even at discount")),"")
A7: Central | B7: 9 | C7: 8 | D7: 1100 | E7: 14 | F7: 65 | G7: =IFERROR(IF(E7=0,0,D7/E7),"") | H7: =IFERROR(IF(C7=0,0,B7/C7),"") | I7: =IFERROR(IF(B7=0,0,D7/B7),"") | J7: =IFERROR(IF(G7<F7,"ABANDON - below breakeven, sell/trade route",IF(G7<F7*1.5,"SURCHARGE - accept only with distance premium","ACCEPT - prime zone, take new customers even at discount")),"")
A8: East | B8: 7 | C8: 10 | D8: 980 | E8: 11 | F8: 65 | G8: =IFERROR(IF(E8=0,0,D8/E8),"") | H8: =IFERROR(IF(C8=0,0,B8/C8),"") | I8: =IFERROR(IF(B8=0,0,D8/B8),"") | J8: =IFERROR(IF(G8<F8,"ABANDON - below breakeven, sell/trade route",IF(G8<F8*1.5,"SURCHARGE - accept only with distance premium","ACCEPT - prime zone, take new customers even at discount")),"")
A9: South | B9: 6 | C9: 7 | D9: 1020 | E9: 9 | F9: 65 | G9: =IFERROR(IF(E9=0,0,D9/E9),"") | H9: =IFERROR(IF(C9=0,0,B9/C9),"") | I9: =IFERROR(IF(B9=0,0,D9/B9),"") | J9: =IFERROR(IF(G9<F9,"ABANDON - below breakeven, sell/trade route",IF(G9<F9*1.5,"SURCHARGE - accept only with distance premium","ACCEPT - prime zone, take new customers even at discount")),"")
A10: Far-West | B10: 3 | C10: 19 | D10: 460 | E10: 12 | F10: 65 | G10: =IFERROR(IF(E10=0,0,D10/E10),"") | H10: =IFERROR(IF(C10=0,0,B10/C10),"") | I10: =IFERROR(IF(B10=0,0,D10/B10),"") | J10: =IFERROR(IF(G10<F10,"ABANDON - below breakeven, sell/trade route",IF(G10<F10*1.5,"SURCHARGE - accept only with distance premium","ACCEPT - prime zone, take new customers even at discount")),"")
G11: =IFERROR(IF(E11=0,0,D11/E11),"") | H11: =IFERROR(IF(C11=0,0,B11/C11),"") | I11: =IFERROR(IF(B11=0,0,D11/B11),"") | J11: =IFERROR(IF(G11<F11,"ABANDON - below breakeven, sell/trade route",IF(G11<F11*1.5,"SURCHARGE - accept only with distance premium","ACCEPT - prime zone, take new customers even at discount")),"")
G12: =IFERROR(IF(E12=0,0,D12/E12),"") | H12: =IFERROR(IF(C12=0,0,B12/C12),"") | I12: =IFERROR(IF(B12=0,0,D12/B12),"") | J12: =IFERROR(IF(G12<F12,"ABANDON - below breakeven, sell/trade route",IF(G12<F12*1.5,"SURCHARGE - accept only with distance premium","ACCEPT - prime zone, take new customers even at discount")),"")
G13: =IFERROR(IF(E13=0,0,D13/E13),"") | H13: =IFERROR(IF(C13=0,0,B13/C13),"") | I13: =IFERROR(IF(B13=0,0,D13/B13),"") | J13: =IFERROR(IF(G13<F13,"ABANDON - below breakeven, sell/trade route",IF(G13<F13*1.5,"SURCHARGE - accept only with distance premium","ACCEPT - prime zone, take new customers even at discount")),"")
G14: =IFERROR(IF(E14=0,0,D14/E14),"") | H14: =IFERROR(IF(C14=0,0,B14/C14),"") | I14: =IFERROR(IF(B14=0,0,D14/B14),"") | J14: =IFERROR(IF(G14<F14,"ABANDON - below breakeven, sell/trade route",IF(G14<F14*1.5,"SURCHARGE - accept only with distance premium","ACCEPT - prime zone, take new customers even at discount")),"")
G15: =IFERROR(IF(E15=0,0,D15/E15),"") | H15: =IFERROR(IF(C15=0,0,B15/C15),"") | I15: =IFERROR(IF(B15=0,0,D15/B15),"") | J15: =IFERROR(IF(G15<F15,"ABANDON - below breakeven, sell/trade route",IF(G15<F15*1.5,"SURCHARGE - accept only with distance premium","ACCEPT - prime zone, take new customers even at discount")),"")
G16: =IFERROR(IF(E16=0,0,D16/E16),"") | H16: =IFERROR(IF(C16=0,0,B16/C16),"") | I16: =IFERROR(IF(B16=0,0,D16/B16),"") | J16: =IFERROR(IF(G16<F16,"ABANDON - below breakeven, sell/trade route",IF(G16<F16*1.5,"SURCHARGE - accept only with distance premium","ACCEPT - prime zone, take new customers even at discount")),"")
G17: =IFERROR(IF(E17=0,0,D17/E17),"") | H17: =IFERROR(IF(C17=0,0,B17/C17),"") | I17: =IFERROR(IF(B17=0,0,D17/B17),"") | J17: =IFERROR(IF(G17<F17,"ABANDON - below breakeven, sell/trade route",IF(G17<F17*1.5,"SURCHARGE - accept only with distance premium","ACCEPT - prime zone, take new customers even at discount")),"")
G18: =IFERROR(IF(E18=0,0,D18/E18),"") | H18: =IFERROR(IF(C18=0,0,B18/C18),"") | I18: =IFERROR(IF(B18=0,0,D18/B18),"") | J18: =IFERROR(IF(G18<F18,"ABANDON - below breakeven, sell/trade route",IF(G18<F18*1.5,"SURCHARGE - accept only with distance premium","ACCEPT - prime zone, take new customers even at discount")),"")
G19: =IFERROR(IF(E19=0,0,D19/E19),"") | H19: =IFERROR(IF(C19=0,0,B19/C19),"") | I19: =IFERROR(IF(B19=0,0,D19/B19),"") | J19: =IFERROR(IF(G19<F19,"ABANDON - below breakeven, sell/trade route",IF(G19<F19*1.5,"SURCHARGE - accept only with distance premium","ACCEPT - prime zone, take new customers even at discount")),"")
G20: =IFERROR(IF(E20=0,0,D20/E20),"") | H20: =IFERROR(IF(C20=0,0,B20/C20),"") | I20: =IFERROR(IF(B20=0,0,D20/B20),"") | J20: =IFERROR(IF(G20<F20,"ABANDON - below breakeven, sell/trade route",IF(G20<F20*1.5,"SURCHARGE - accept only with distance premium","ACCEPT - prime zone, take new customers even at discount")),"")
G21: =IFERROR(IF(E21=0,0,D21/E21),"") | H21: =IFERROR(IF(C21=0,0,B21/C21),"") | I21: =IFERROR(IF(B21=0,0,D21/B21),"") | J21: =IFERROR(IF(G21<F21,"ABANDON - below breakeven, sell/trade route",IF(G21<F21*1.5,"SURCHARGE - accept only with distance premium","ACCEPT - prime zone, take new customers even at discount")),"")
G22: =IFERROR(IF(E22=0,0,D22/E22),"") | H22: =IFERROR(IF(C22=0,0,B22/C22),"") | I22: =IFERROR(IF(B22=0,0,D22/B22),"") | J22: =IFERROR(IF(G22<F22,"ABANDON - below breakeven, sell/trade route",IF(G22<F22*1.5,"SURCHARGE - accept only with distance premium","ACCEPT - prime zone, take new customers even at discount")),"")
... G25: =IFERROR(IF(E25=0,0,D25/E25),"") | H25: =IFERROR(IF(C25=0,0,B25/C25),"") | I25: =IFERROR(IF(B25=0,0,D25/B25),"") | J25: =IFERROR(IF(G25<F25,"ABANDON - below breakeven, sell/trade route",IF(G25<F25*1.5,"SURCHARGE - accept only with distance premium","ACCEPT - prime zone, take new customers even at discount")),"")

Sheet New Customer Calculator
A1: AI INSIGHT SUMMARY: Your North zone yields $142/drive-hour with 12 stops packed into 6 miles -- this is your profit engine; accept any new customer here, even at a 15% discount. Your Far-West zone yields only $38/drive-hour across 3 scattered stops over 19 miles, which is below your $65/hour breakeven -- decline new west-side prospects unless they accept a $40 distance premium. The West territory as a whole has crossed into abandon economics; selling or trading those 3 stops to a competitor would free 4.2 drive-hours per week. Apply the New Customer Calculator before booking any prospect: it scored the sample prospect in Zone 4 as DECLINE because their zone yields under breakeven and adding them lengthens an already thin route.
A5: Prospect Name | B5: Prospect Zone | C5: Quoted Monthly Price | D5: Extra Drive Time Added (min) | E5: Zone Revenue per Drive-Hour | F5: Breakeven $/Drive-Hour | G5: Marginal $/Drive-Hour | H5: Required Distance Premium | I5: Booking Decision
A6: Johnson | B6: North | C6: 95 | D6: 5 | E6: =IFERROR(VLOOKUP(B6,'Zone Density Dashboard'!A:G,7,FALSE),0) | F6: 65 | G6: =IFERROR(IF(D6=0,C6*4,C6/(D6/60)),"") | H6: =IFERROR(MAX(0,ROUND(((F6-G6)*(D6/60)),0)),"") | I6: =IFERROR(IF(G6>=F6*1.5,"ACCEPT - profitable in this zone",IF(G6>=F6,"ACCEPT WITH CARE - thin margin, prefer same zone","DECLINE unless they pay +$"&H6&"/mo premium")),"")
A7: Alvarez | B7: Central | C7: 80 | D7: 18 | E7: =IFERROR(VLOOKUP(B7,'Zone Density Dashboard'!A:G,7,FALSE),0) | F7: 65 | G7: =IFERROR(IF(D7=0,C7*4,C7/(D7/60)),"") | H7: =IFERROR(MAX(0,ROUND(((F7-G7)*(D7/60)),0)),"") | I7: =IFERROR(IF(G7>=F7*1.5,"ACCEPT - profitable in this zone",IF(G7>=F7,"ACCEPT WITH CARE - thin margin, prefer same zone","DECLINE unless they pay +$"&H7&"/mo premium")),"")
A8: Becker | B8: East | C8: 70 | D8: 35 | E8: =IFERROR(VLOOKUP(B8,'Zone Density Dashboard'!A:G,7,FALSE),0) | F8: 65 | G8: =IFERROR(IF(D8=0,C8*4,C8/(D8/60)),"") | H8: =IFERROR(MAX(0,ROUND(((F8-G8)*(D8/60)),0)),"") | I8: =IFERROR(IF(G8>=F8*1.5,"ACCEPT - profitable in this zone",IF(G8>=F8,"ACCEPT WITH CARE - thin margin, prefer same zone","DECLINE unless they pay +$"&H8&"/mo premium")),"")
A9: Tran | B9: Far-West | C9: 75 | D9: 42 | E9: =IFERROR(VLOOKUP(B9,'Zone Density Dashboard'!A:G,7,FALSE),0) | F9: 65 | G9: =IFERROR(IF(D9=0,C9*4,C9/(D9/60)),"") | H9: =IFERROR(MAX(0,ROUND(((F9-G9)*(D9/60)),0)),"") | I9: =IFERROR(IF(G9>=F9*1.5,"ACCEPT - profitable in this zone",IF(G9>=F9,"ACCEPT WITH CARE - thin margin, prefer same zone","DECLINE unless they pay +$"&H9&"/mo premium")),"")
A10: Williams | B10: Far-West | C10: 45 | D10: 55 | E10: =IFERROR(VLOOKUP(B10,'Zone Density Dashboard'!A:G,7,FALSE),0) | F10: 65 | G10: =IFERROR(IF(D10=0,C10*4,C10/(D10/60)),"") | H10: =IFERROR(MAX(0,ROUND(((F10-G10)*(D10/60)),0)),"") | I10: =IFERROR(IF(G10>=F10*1.5,"ACCEPT - profitable in this zone",IF(G10>=F10,"ACCEPT WITH CARE - thin margin, prefer same zone","DECLINE unless they pay +$"&H10&"/mo premium")),"")
E11: =IFERROR(VLOOKUP(B11,'Zone Density Dashboard'!A:G,7,FALSE),0) | G11: =IFERROR(IF(D11=0,C11*4,C11/(D11/60)),"") | H11: =IFERROR(MAX(0,ROUND(((F11-G11)*(D11/60)),0)),"") | I11: =IFERROR(IF(G11>=F11*1.5,"ACCEPT - profitable in this zone",IF(G11>=F11,"ACCEPT WITH CARE - thin margin, prefer same zone","DECLINE unless they pay +$"&H11&"/mo premium")),"")
E12: =IFERROR(VLOOKUP(B12,'Zone Density Dashboard'!A:G,7,FALSE),0) | G12: =IFERROR(IF(D12=0,C12*4,C12/(D12/60)),"") | H12: =IFERROR(MAX(0,ROUND(((F12-G12)*(D12/60)),0)),"") | I12: =IFERROR(IF(G12>=F12*1.5,"ACCEPT - profitable in this zone",IF(G12>=F12,"ACCEPT WITH CARE - thin margin, prefer same zone","DECLINE unless they pay +$"&H12&"/mo premium")),"")
E13: =IFERROR(VLOOKUP(B13,'Zone Density Dashboard'!A:G,7,FALSE),0) | G13: =IFERROR(IF(D13=0,C13*4,C13/(D13/60)),"") | H13: =IFERROR(MAX(0,ROUND(((F13-G13)*(D13/60)),0)),"") | I13: =IFERROR(IF(G13>=F13*1.5,"ACCEPT - profitable in this zone",IF(G13>=F13,"ACCEPT WITH CARE - thin margin, prefer same zone","DECLINE unless they pay +$"&H13&"/mo premium")),"")
E14: =IFERROR(VLOOKUP(B14,'Zone Density Dashboard'!A:G,7,FALSE),0) | G14: =IFERROR(IF(D14=0,C14*4,C14/(D14/60)),"") | H14: =IFERROR(MAX(0,ROUND(((F14-G14)*(D14/60)),0)),"") | I14: =IFERROR(IF(G14>=F14*1.5,"ACCEPT - profitable in this zone",IF(G14>=F14,"ACCEPT WITH CARE - thin margin, prefer same zone","DECLINE unless they pay +$"&H14&"/mo premium")),"")
E15: =IFERROR(VLOOKUP(B15,'Zone Density Dashboard'!A:G,7,FALSE),0) | G15: =IFERROR(IF(D15=0,C15*4,C15/(D15/60)),"") | H15: =IFERROR(MAX(0,ROUND(((F15-G15)*(D15/60)),0)),"") | I15: =IFERROR(IF(G15>=F15*1.5,"ACCEPT - profitable in this zone",IF(G15>=F15,"ACCEPT WITH CARE - thin margin, prefer same zone","DECLINE unless they pay +$"&H15&"/mo premium")),"")
E16: =IFERROR(VLOOKUP(B16,'Zone Density Dashboard'!A:G,7,FALSE),0) | G16: =IFERROR(IF(D16=0,C16*4,C16/(D16/60)),"") | H16: =IFERROR(MAX(0,ROUND(((F16-G16)*(D16/60)),0)),"") | I16: =IFERROR(IF(G16>=F16*1.5,"ACCEPT - profitable in this zone",IF(G16>=F16,"ACCEPT WITH CARE - thin margin, prefer same zone","DECLINE unless they pay +$"&H16&"/mo premium")),"")
E17: =IFERROR(VLOOKUP(B17,'Zone Density Dashboard'!A:G,7,FALSE),0) | G17: =IFERROR(IF(D17=0,C17*4,C17/(D17/60)),"") | H17: =IFERROR(MAX(0,ROUND(((F17-G17)*(D17/60)),0)),"") | I17: =IFERROR(IF(G17>=F17*1.5,"ACCEPT - profitable in this zone",IF(G17>=F17,"ACCEPT WITH CARE - thin margin, prefer same zone","DECLINE unless they pay +$"&H17&"/mo premium")),"")
E18: =IFERROR(VLOOKUP(B18,'Zone Density Dashboard'!A:G,7,FALSE),0) | G18: =IFERROR(IF(D18=0,C18*4,C18/(D18/60)),"") | H18: =IFERROR(MAX(0,ROUND(((F18-G18)*(D18/60)),0)),"") | I18: =IFERROR(IF(G18>=F18*1.5,"ACCEPT - profitable in this zone",IF(G18>=F18,"ACCEPT WITH CARE - thin margin, prefer same zone","DECLINE unless they pay +$"&H18&"/mo premium")),"")
E19: =IFERROR(VLOOKUP(B19,'Zone Density Dashboard'!A:G,7,FALSE),0) | G19: =IFERROR(IF(D19=0,C19*4,C19/(D19/60)),"") | H19: =IFERROR(MAX(0,ROUND(((F19-G19)*(D19/60)),0)),"") | I19: =IFERROR(IF(G19>=F19*1.5,"ACCEPT - profitable in this zone",IF(G19>=F19,"ACCEPT WITH CARE - thin margin, prefer same zone","DECLINE unless they pay +$"&H19&"/mo premium")),"")
E20: =IFERROR(VLOOKUP(B20,'Zone Density Dashboard'!A:G,7,FALSE),0) | G20: =IFERROR(IF(D20=0,C20*4,C20/(D20/60)),"") | H20: =IFERROR(MAX(0,ROUND(((F20-G20)*(D20/60)),0)),"") | I20: =IFERROR(IF(G20>=F20*1.5,"ACCEPT - profitable in this zone",IF(G20>=F20,"ACCEPT WITH CARE - thin margin, prefer same zone","DECLINE unless they pay +$"&H20&"/mo premium")),"")
E21: =IFERROR(VLOOKUP(B21,'Zone Density Dashboard'!A:G,7,FALSE),0) | G21: =IFERROR(IF(D21=0,C21*4,C21/(D21/60)),"") | H21: =IFERROR(MAX(0,ROUND(((F21-G21)*(D21/60)),0)),"") | I21: =IFERROR(IF(G21>=F21*1.5,"ACCEPT - profitable in this zone",IF(G21>=F21,"ACCEPT WITH CARE - thin margin, prefer same zone","DECLINE unless they pay +$"&H21&"/mo premium")),"")
E22: =IFERROR(VLOOKUP(B22,'Zone Density Dashboard'!A:G,7,FALSE),0) | G22: =IFERROR(IF(D22=0,C22*4,C22/(D22/60)),"") | H22: =IFERROR(MAX(0,ROUND(((F22-G22)*(D22/60)),0)),"") | I22: =IFERROR(IF(G22>=F22*1.5,"ACCEPT - profitable in this zone",IF(G22>=F22,"ACCEPT WITH CARE - thin margin, prefer same zone","DECLINE unless they pay +$"&H22&"/mo premium")),"")
... E25: =IFERROR(VLOOKUP(B25,'Zone Density Dashboard'!A:G,7,FALSE),0) | G25: =IFERROR(IF(D25=0,C25*4,C25/(D25/60)),"") | H25: =IFERROR(MAX(0,ROUND(((F25-G25)*(D25/60)),0)),"") | I25: =IFERROR(IF(G25>=F25*1.5,"ACCEPT - profitable in this zone",IF(G25>=F25,"ACCEPT WITH CARE - thin margin, prefer same zone","DECLINE unless they pay +$"&H25&"/mo premium")),"")

Sheet Min Price by Distance
A1: AI INSIGHT SUMMARY: Your North zone yields $142/drive-hour with 12 stops packed into 6 miles -- this is your profit engine; accept any new customer here, even at a 15% discount. Your Far-West zone yields only $38/drive-hour across 3 scattered stops over 19 miles, which is below your $65/hour breakeven -- decline new west-side prospects unless they accept a $40 distance premium. The West territory as a whole has crossed into abandon economics; selling or trading those 3 stops to a competitor would free 4.2 drive-hours per week. Apply the New Customer Calculator before booking any prospect: it scored the sample prospect in Zone 4 as DECLINE because their zone yields under breakeven and adding them lengthens an already thin route.
A5: Distance Band (miles) | B5: Round-Trip Drive Time (min) | C5: Breakeven $/Drive-Hour | D5: Drive Cost to Serve | E5: Minimum Monthly Price | F5: Recommended Price (with margin) | G5: Pricing Rule
A6: 0-3 | B6: 10 | C6: 65 | D6: =IFERROR(ROUND(B6/60*C6,2),"") | E6: =IFERROR(ROUND(D6*4.33,0),"") | F6: =IFERROR(ROUND(E6*1.35,0),"") | G6: =IFERROR(IF(B6>60,"Quote at least $"&F6&" or decline","Standard zone pricing applies, min $"&E6),"")
A7: 4-7 | B7: 22 | C7: 65 | D7: =IFERROR(ROUND(B7/60*C7,2),"") | E7: =IFERROR(ROUND(D7*4.33,0),"") | F7: =IFERROR(ROUND(E7*1.35,0),"") | G7: =IFERROR(IF(B7>60,"Quote at least $"&F7&" or decline","Standard zone pricing applies, min $"&E7),"")
A8: 8-12 | B8: 38 | C8: 65 | D8: =IFERROR(ROUND(B8/60*C8,2),"") | E8: =IFERROR(ROUND(D8*4.33,0),"") | F8: =IFERROR(ROUND(E8*1.35,0),"") | G8: =IFERROR(IF(B8>60,"Quote at least $"&F8&" or decline","Standard zone pricing applies, min $"&E8),"")
A9: 13-18 | B9: 56 | C9: 65 | D9: =IFERROR(ROUND(B9/60*C9,2),"") | E9: =IFERROR(ROUND(D9*4.33,0),"") | F9: =IFERROR(ROUND(E9*1.35,0),"") | G9: =IFERROR(IF(B9>60,"Quote at least $"&F9&" or decline","Standard zone pricing applies, min $"&E9),"")
A10: 19+ | B10: 75 | C10: 65 | D10: =IFERROR(ROUND(B10/60*C10,2),"") | E10: =IFERROR(ROUND(D10*4.33,0),"") | F10: =IFERROR(ROUND(E10*1.35,0),"") | G10: =IFERROR(IF(B10>60,"Quote at least $"&F10&" or decline","Standard zone pricing applies, min $"&E10),"")
D11: =IFERROR(ROUND(B11/60*C11,2),"") | E11: =IFERROR(ROUND(D11*4.33,0),"") | F11: =IFERROR(ROUND(E11*1.35,0),"") | G11: =IFERROR(IF(B11>60,"Quote at least $"&F11&" or decline","Standard zone pricing applies, min $"&E11),"")
D12: =IFERROR(ROUND(B12/60*C12,2),"") | E12: =IFERROR(ROUND(D12*4.33,0),"") | F12: =IFERROR(ROUND(E12*1.35,0),"") | G12: =IFERROR(IF(B12>60,"Quote at least $"&F12&" or decline","Standard zone pricing applies, min $"&E12),"")
D13: =IFERROR(ROUND(B13/60*C13,2),"") | E13: =IFERROR(ROUND(D13*4.33,0),"") | F13: =IFERROR(ROUND(E13*1.35,0),"") | G13: =IFERROR(IF(B13>60,"Quote at least $"&F13&" or decline","Standard zone pricing applies, min $"&E13),"")
D14: =IFERROR(ROUND(B14/60*C14,2),"") | E14: =IFERROR(ROUND(D14*4.33,0),"") | F14: =IFERROR(ROUND(E14*1.35,0),"") | G14: =IFERROR(IF(B14>60,"Quote at least $"&F14&" or decline","Standard zone pricing applies, min $"&E14),"")
D15: =IFERROR(ROUND(B15/60*C15,2),"") | E15: =IFERROR(ROUND(D15*4.33,0),"") | F15: =IFERROR(ROUND(E15*1.35,0),"") | G15: =IFERROR(IF(B15>60,"Quote at least $"&F15&" or decline","Standard zone pricing applies, min $"&E15),"")
D16: =IFERROR(ROUND(B16/60*C16,2),"") | E16: =IFERROR(ROUND(D16*4.33,0),"") | F16: =IFERROR(ROUND(E16*1.35,0),"") | G16: =IFERROR(IF(B16>60,"Quote at least $"&F16&" or decline","Standard zone pricing applies, min $"&E16),"")
D17: =IFERROR(ROUND(B17/60*C17,2),"") | E17: =IFERROR(ROUND(D17*4.33,0),"") | F17: =IFERROR(ROUND(E17*1.35,0),"") | G17: =IFERROR(IF(B17>60,"Quote at least $"&F17&" or decline","Standard zone pricing applies, min $"&E17),"")
D18: =IFERROR(ROUND(B18/60*C18,2),"") | E18: =IFERROR(ROUND(D18*4.33,0),"") | F18: =IFERROR(ROUND(E18*1.35,0),"") | G18: =IFERROR(IF(B18>60,"Quote at least $"&F18&" or decline","Standard zone pricing applies, min $"&E18),"")
D19: =IFERROR(ROUND(B19/60*C19,2),"") | E19: =IFERROR(ROUND(D19*4.33,0),"") | F19: =IFERROR(ROUND(E19*1.35,0),"") | G19: =IFERROR(IF(B19>60,"Quote at least $"&F19&" or decline","Standard zone pricing applies, min $"&E19),"")
D20: =IFERROR(ROUND(B20/60*C20,2),"") | E20: =IFERROR(ROUND(D20*4.33,0),"") | F20: =IFERROR(ROUND(E20*1.35,0),"") | G20: =IFERROR(IF(B20>60,"Quote at least $"&F20&" or decline","Standard zone pricing applies, min $"&E20),"")
D21: =IFERROR(ROUND(B21/60*C21,2),"") | E21: =IFERROR(ROUND(D21*4.33,0),"") | F21: =IFERROR(ROUND(E21*1.35,0),"") | G21: =IFERROR(IF(B21>60,"Quote at least $"&F21&" or decline","Standard zone pricing applies, min $"&E21),"")
D22: =IFERROR(ROUND(B22/60*C22,2),"") | E22: =IFERROR(ROUND(D22*4.33,0),"") | F22: =IFERROR(ROUND(E22*1.35,0),"") | G22: =IFERROR(IF(B22>60,"Quote at least $"&F22&" or decline","Standard zone pricing applies, min $"&E22),"")
... D25: =IFERROR(ROUND(B25/60*C25,2),"") | E25: =IFERROR(ROUND(D25*4.33,0),"") | F25: =IFERROR(ROUND(E25*1.35,0),"") | G25: =IFERROR(IF(B25>60,"Quote at least $"&F25&" or decline","Standard zone pricing applies, min $"&E25),"")
